tvmer/__init__.py
tvmer/__main__.py
tvmer/utils.py
tvmer-0.1.2.dist-info/entry_points.txt
tvmer-0.1.2.dist-info/WHEEL
tvmer-0.1.2.dist-info/METADATA
tvmer-0.1.2.dist-info/RECORD
