Metadata-Version: 2.1
Name: tvmer
Version: 0.1.2
License: MIT
Author-email: zrr1999 <2742392377@qq.com>
Requires-Python: >=3.8
Requires-Dist: apache-tvm
Requires-Dist: rich
Requires-Dist: typer
